[{"line":1,"elements":[{"start_timestamp":"2022-12-10T12:45:11.496Z","line":3,"name":"Retail website Login test","description":"","id":"login-to-retail-website;retail-website-login-test","type":"scenario","keyword":"Scenario","steps":[{"result":{"status":"undefined"},"line":4,"name":"user on retail website","match":{},"keyword":"Given "},{"result":{"status":"skipped"},"line":5,"name":"user click on MyAccount","match":{},"keyword":"When "},{"result":{"status":"skipped"},"line":6,"name":"user enter userName 'saad1@test.com'","match":{},"keyword":"And "},{"result":{"duration":1000600,"status":"skipped"},"line":7,"name":"user enter password 'test1234'","match":{},"keyword":"And "},{"result":{"status":"skipped"},"line":8,"name":"user click on login button","match":{},"keyword":"And "},{"result":{"status":"skipped"},"line":9,"name":"user should be logged in to MyAccount dashboard","match":{},"keyword":"Then "}],"tags":[{"name":"@smokeTest"}]}],"name":"Login to retail Website","description":"","id":"login-to-retail-website","keyword":"Feature","uri":"classpath:features/login.feature","tags":[]}]